sagax/__init__.py
sagax/api.py
sagax/authentication.py
sagax/config.py
sagax/ldap.py
sagax/logs.py
sagax/middleware.py
sagax/plugins.py
sagax/sensu.py
sagax/tokens.py
sagax-0.1.0.dist-info/DESCRIPTION.rst
sagax-0.1.0.dist-info/METADATA
sagax-0.1.0.dist-info/RECORD
sagax-0.1.0.dist-info/WHEEL
sagax-0.1.0.dist-info/entry_points.txt
sagax-0.1.0.dist-info/metadata.json
sagax-0.1.0.dist-info/top_level.txt
sagax-frontend/.babelrc
sagax-frontend/.editorconfig
sagax-frontend/.eslintignore
sagax-frontend/.eslintrc.js
sagax-frontend/.gitignore
sagax-frontend/.postcssrc.js
sagax-frontend/README.md
sagax-frontend/index.html
sagax-frontend/package.json
sagax-frontend/yarn.lock
sagax-frontend/build/build.js
sagax-frontend/build/check-versions.js
sagax-frontend/build/logo.png
sagax-frontend/build/utils.js
sagax-frontend/build/vue-loader.conf.js
sagax-frontend/build/webpack.base.conf.js
sagax-frontend/build/webpack.dev.conf.js
sagax-frontend/build/webpack.prod.conf.js
sagax-frontend/config/dev.env.js
sagax-frontend/config/index.js
sagax-frontend/config/prod.env.js
sagax-frontend/config/test.env.js
sagax-frontend/dist/index.html
sagax-frontend/dist/static/css/app.ffc8f977b6b56c13f96b71bc2ed74526.css
sagax-frontend/dist/static/css/app.ffc8f977b6b56c13f96b71bc2ed74526.css.map
sagax-frontend/dist/static/fonts/Simple-Line-Icons.0cb0b9c.woff2
sagax-frontend/dist/static/fonts/Simple-Line-Icons.78f07e2.woff
sagax-frontend/dist/static/fonts/Simple-Line-Icons.d228596.ttf
sagax-frontend/dist/static/fonts/Simple-Line-Icons.f33df36.eot
sagax-frontend/dist/static/fonts/fontawesome-webfont.674f50d.eot
sagax-frontend/dist/static/fonts/fontawesome-webfont.af7ae50.woff2
sagax-frontend/dist/static/fonts/fontawesome-webfont.b06871f.ttf
sagax-frontend/dist/static/fonts/fontawesome-webfont.fee66e7.woff
sagax-frontend/dist/static/img/Simple-Line-Icons.2fe2efe.svg
sagax-frontend/dist/static/img/fontawesome-webfont.912ec66.svg
sagax-frontend/dist/static/img/logo-symbol.png
sagax-frontend/dist/static/img/logo.8eb6523.png
sagax-frontend/dist/static/img/logo.png
sagax-frontend/dist/static/js/app.f37f3eeb9864e5546821.js
sagax-frontend/dist/static/js/app.f37f3eeb9864e5546821.js.map
