Metadata-Version: 2.0
Name: sagax
Version: 0.1.0
Summary: Sensu dashboard
Home-page: https://github.com/joshbenner/sagax
Author: Josh Benner
Author-email: josh@bennerweb.com
License: BSD
Platform: UNKNOWN
Classifier: Development Status :: 4 - Beta
Classifier: License :: OSI Approved :: BSD License
Classifier: Operating System :: OS Independent
Classifier: Programming Language :: Python
Classifier: Programming Language :: Python :: 3.5
Classifier: Programming Language :: Python :: 3.6
Classifier: Programming Language :: Python :: Implementation :: CPython
Classifier: Programming Language :: Python :: Implementation :: PyPy
Classifier: Topic :: Internet :: WWW/HTTP
Classifier: Topic :: System :: Monitoring
Requires-Dist: hug (<3,>=2.4)
Requires-Dist: falcon
Requires-Dist: requests (<3,>=2.18)
Requires-Dist: configmanager (<2,>=1.34)
Requires-Dist: pyyaml (<4,>=3.12)
Requires-Dist: pyjwt (<2,>=1.6.0)
Provides-Extra: ldap
Requires-Dist: ldap3 (<3,>=2.4); extra == 'ldap'
Provides-Extra: test
Requires-Dist: pytest; extra == 'test'
